sqlite2csv/__init__.py
sqlite2csv/__main__.py
sqlite2csv/lib/__init__.py
sqlite2csv/lib/logger.py
sqlite2csv/lib/pandas.py
sqlite2csv/lib/sqlalchemy.py
sqlite2csv-0.2.0.dist-info/METADATA
sqlite2csv-0.2.0.dist-info/WHEEL
sqlite2csv-0.2.0.dist-info/entry_points.txt
sqlite2csv-0.2.0.dist-info/licenses/LICENSE
sqlite2csv-0.2.0.dist-info/RECORD
