Metadata-Version: 2.3
Name: sqlite2csv
Version: 0.2.0
Summary: Export data from a SQLite database to CSV files.
Project-URL: Homepage, https://github.com/ryohidaka/sqlite2csv
Project-URL: Repository, https://github.com/ryohidaka/sqlite2csv
Project-URL: Issues, https://github.com/ryohidaka/sqlite2csv/issues
Project-URL: Changelog, https://github.com/ryohidaka/blob/main/sqlite2csv/CHANGELOG.md
Author-email: ryohidaka <39184410+ryohidaka@users.noreply.github.com>
License: MIT License
License-File: LICENSE
Keywords: conversion,copy,csv,sqlite,tool
Requires-Python: >=3.8
Requires-Dist: pandas>=2.2.2
Requires-Dist: sqlalchemy>=2.0.31
